flask_servicenow
