Metadata-Version: 1.1
Name: flask-servicenow
Version: 0.1.1
Summary: ServiceNow REST API Flask extension
Home-page: https://github.com/rbw0/flask-servicenow
Author: Robert Wikman
Author-email: rbw@vault13.org
License: GPLv2
Download-URL: https://github.com/rbw0/flask-servicenow/tarball/0.1.1
Keywords: servicenow,rest,api,flask
Platform: UNKNOWN
